{
    "1184506390212001832": {
        "title": [
            "???",
            "???"
        ],
        "point": [
            {},
            {
                "577266050769485844": 10
            }
        ],
        "option": {
            "point": true,
            "user_count": true
        }
    },
    "1185950902285246465": {
        "title": [
            "???",
            "???"
        ],
        "point": [
            {},
            {}
        ],
        "option": {
            "point": true,
            "user_count": true
        }
    },
    "1185967182543323267": {
        "title": [
            "aaa",
            "bbb"
        ],
        "point": [
            {},
            {}
        ],
        "option": {
            "point": true,
            "user_count": true
        }
    },
    "1187958945113972777": {
        "title": [
            "\u3141\u3141\u3141",
            "\u3160\u3160\u3160"
        ],
        "point": [
            {
                "577266050769485844": 100,
                "577266050769485843": 100,
                "577266050769485842": 100
            },
            {}
        ],
        "option": {
            "point": false,
            "user_count": false
        }
    }
}